jupyterlab_scheduler/__init__.py
jupyterlab_scheduler/_version.py
jupyterlab_scheduler/handlers.py
jupyterlab_scheduler/labextension/jupyterlab_scheduler-0.0.1.tgz
jupyterlab_scheduler/labextension/jupyterlab_scheduler-0.1.1.tgz
jupyterlab_scheduler/labextension/jupyterlab_scheduler-0.1.2.tgz
jupyterlab_scheduler/labextension/jupyterlab_scheduler-0.1.3.tgz
jupyterlab_scheduler/labextension/jupyterlab_scheduler-0.1.4.tgz
jupyterlab_scheduler/labextension/jupyterlab_scheduler-0.1.5.tgz
jupyterlab_scheduler-0.1.5.data/data/etc/jupyter/jupyter_notebook_config.d/jupyterlab_scheduler.json
jupyterlab_scheduler-0.1.5.data/data/share/jupyter/lab/extensions/jupyterlab_scheduler-0.0.1.tgz
jupyterlab_scheduler-0.1.5.data/data/share/jupyter/lab/extensions/jupyterlab_scheduler-0.1.1.tgz
jupyterlab_scheduler-0.1.5.data/data/share/jupyter/lab/extensions/jupyterlab_scheduler-0.1.2.tgz
jupyterlab_scheduler-0.1.5.data/data/share/jupyter/lab/extensions/jupyterlab_scheduler-0.1.3.tgz
jupyterlab_scheduler-0.1.5.data/data/share/jupyter/lab/extensions/jupyterlab_scheduler-0.1.4.tgz
jupyterlab_scheduler-0.1.5.data/data/share/jupyter/lab/extensions/jupyterlab_scheduler-0.1.5.tgz
jupyterlab_scheduler-0.1.5.dist-info/LICENSE
jupyterlab_scheduler-0.1.5.dist-info/METADATA
jupyterlab_scheduler-0.1.5.dist-info/WHEEL
jupyterlab_scheduler-0.1.5.dist-info/top_level.txt
jupyterlab_scheduler-0.1.5.dist-info/RECORD
