Metadata-Version: 2.1
Name: jupyterlab-scheduler
Version: 0.1.5
Summary: CRON scheduler for Jupyter Lab
Home-page: https://github.com/tiburon-security/jupyterlab_scheduler
Author: Jovanni Hernandez
License: MIT
Keywords: Jupyter,JupyterLab
Platform: Linux
Platform: Mac OS X
Platform: Windows
Classifier: License :: OSI Approved :: BSD License
Classifier: Programming Language :: Python
Classifier: Programming Language :: Python :: 3
Classifier: Programming Language :: Python :: 3.5
Classifier: Programming Language :: Python :: 3.6
Classifier: Programming Language :: Python :: 3.7
Classifier: Programming Language :: Python :: 3.8
Classifier: Framework :: Jupyter
Requires-Dist: jupyterlab (~=3.1.4)
Requires-Dist: python-crontab (~=2.5)
Requires-Dist: papermill (~=2.1)
